odoo/addons/event_quick_registration/README.rst
odoo/addons/event_quick_registration/__init__.py
odoo/addons/event_quick_registration/__manifest__.py
odoo/addons/event_quick_registration/i18n/es.po
odoo/addons/event_quick_registration/i18n/event_quick_registration.pot
odoo/addons/event_quick_registration/i18n/it.po
odoo/addons/event_quick_registration/readme/CONTRIBUTORS.rst
odoo/addons/event_quick_registration/readme/DESCRIPTION.rst
odoo/addons/event_quick_registration/readme/USAGE.rst
odoo/addons/event_quick_registration/static/description/icon.png
odoo/addons/event_quick_registration/static/description/index.html
odoo/addons/event_quick_registration/views/event_event.xml
odoo/addons/event_quick_registration/wizard/__init__.py
odoo/addons/event_quick_registration/wizard/event_quick_registration.py
odoo/addons/event_quick_registration/wizard/event_quick_registration.xml
odoo_addon_event_quick_registration-15.0.1.0.0.9.dist-info/METADATA
odoo_addon_event_quick_registration-15.0.1.0.0.9.dist-info/WHEEL
odoo_addon_event_quick_registration-15.0.1.0.0.9.dist-info/top_level.txt
odoo_addon_event_quick_registration-15.0.1.0.0.9.dist-info/RECORD
